librairy/__init__.py
librairy/bookshelf.py
librairy/config.py
librairy/collector/semscholar.py
librairy-0.0.2.dist-info/LICENSE
librairy-0.0.2.dist-info/METADATA
librairy-0.0.2.dist-info/WHEEL
librairy-0.0.2.dist-info/top_level.txt
librairy-0.0.2.dist-info/RECORD
