Metadata-Version: 2.1
Name: librairy
Version: 0.0.2
Summary: Seamless integration with the librAIry system, enabling developers to harness powerful AI capabilities for managing and analyzing large-scale multilingual documents with ease.
Author-email: Carlos Badenes-Olmedo <cbadenes@gmail.com>
Project-URL: Homepage, https://github.com/librairy/driver
Project-URL: Bug Tracker, https://github.com/librairy/driver/issues
Classifier: Programming Language :: Python :: 3
Classifier: License :: OSI Approved :: Apache Software License
Classifier: Operating System :: OS Independent
Classifier: Topic :: Internet :: WWW/HTTP :: Indexing/Search
Classifier: Natural Language :: English
Classifier: Topic :: Software Development :: Libraries
Requires-Python: >=3.7
License-File: LICENSE
Requires-Dist: requests
